Metadata-Version: 1.1
Name: mockbcrypt
Version: 0.2.3
Summary: A bcrypt mock plugin for nosetests
Home-page: https://github.com/boneyao/mockbcrypt
Author: Bone Yao
Author-email: UNKNOWN
License: MIT
Platform: UNKNOWN
Classifier: Intended Audience :: Developers
Classifier: License :: OSI Approved :: MIT License
Classifier: Natural Language :: English
Classifier: Operating System :: OS Independent
Classifier: Programming Language :: Python
Classifier: Programming Language :: Python :: 2.7
Classifier: Topic :: Software Development :: Testing
Classifier: Environment :: Console
